nbtest/__init__.py
nbtest/nbtest.py
nbtest/python3-test-kernel.py
nbtest/python3-test/kernel.json
elastic_nbtest-0.3.0.dist-info/LICENSE
elastic_nbtest-0.3.0.dist-info/METADATA
elastic_nbtest-0.3.0.dist-info/NOTICE
elastic_nbtest-0.3.0.dist-info/WHEEL
elastic_nbtest-0.3.0.dist-info/entry_points.txt
elastic_nbtest-0.3.0.dist-info/top_level.txt
elastic_nbtest-0.3.0.dist-info/RECORD
