Metadata-Version: 2.1
Name: elastic-nbtest
Version: 0.3.0
Summary: Notebook testing tool from Elastic's Search Labs
Author-email: Miguel Grinberg <miguel.grinberg@elastic.co>
Maintainer-email: Miguel Grinberg <miguel.grinberg@elastic.co>, Joe McElroy <joseph.mcelroy@elastic.co>, Max Jakob <max.jakob@elastic.co>
License: Apache License
Project-URL: Homepage, https://github.com/elastic/nbtest
Project-URL: Bug Tracker, https://github.com/elastic/nbtest/issues
Requires-Python: >=3.6
License-File: LICENSE
License-File: NOTICE
Requires-Dist: jupyter
Requires-Dist: rich
Requires-Dist: pyyaml
Requires-Dist: python-dotenv
